brivo/__init__.py
brivo/app.py
brivo/async_app.py
brivo/base_app.py
brivo/models/__init__.py
brivo/models/auth.py
brivo/models/base.py
brivo/models/company.py
brivo/models/request_factory.py
brivo/models/unit.py
brivo/models/users.py
brivo_smarthome-0.0.1a9.dist-info/LICENSE
brivo_smarthome-0.0.1a9.dist-info/METADATA
brivo_smarthome-0.0.1a9.dist-info/WHEEL
brivo_smarthome-0.0.1a9.dist-info/RECORD
