Metadata-Version: 2.3
Name: brivo-smarthome
Version: 0.0.1a9
Summary: Library for interacting with Brivo's API.
License: MIT
Author: Anthony DeGarimore
Author-email: Anthony@DeGarimore.com
Maintainer: Anthony DeGarimore
Maintainer-email: Anthony@DeGarimore.com
Requires-Python: >=3.13
Classifier: License :: OSI Approved :: MIT License
Classifier: Programming Language :: Python :: 3
Classifier: Programming Language :: Python :: 3.13
Provides-Extra: dev
Requires-Dist: httpx (>=0.28.1)
Requires-Dist: pydantic (>=2.11)
Requires-Dist: pytest ; extra == "dev"
Project-URL: Bug Tracker, https://github.com/Paso-Robles-Vacation-Rentals/brivo-smarthome-python/issues
Project-URL: Repository, https://github.com/Paso-Robles-Vacation-Rentals/brivo-smarthome-python
